{
  "name": "Rodney Sandoval",
  "age": 45,
  "address": {
    "street": "Madziw Ridge",
    "city": "Mudseres",
    "state": "WY",
    "zip": "42774"
  },
  "contact": {
    "phone": "(379) 247-5126",
    "servicePhone": "800833525"
  },
  "birthday": "1964-01-10T20:25:45.663Z",
  "ip": "81.0.169.110",
  "foo": "bar",
  "profile": {
    "about": "Non ohevar jabel mu lik fetkil kej bojo zenusus jijebi tozzu ted miz cabjug. Muwev ledez aro peaneev mepdez uhhepavu ofegebo wuggij dusabaj halibi tiefiesi fukudgi mit gigjesdog. Ji odig suf zuserju dob wujob dahrecuf ho iwibul fepuk lug rinkatok hojnar fusdas me tepmolvis. Teltozi pabib gis ufaka ed tusfufi ofte ranfosis ipfow wev rimwo ba womzouha fe jehabozi.",
    "bio": "Pup bacwu saajkit eziman teni ut or cojzawzab upa gi azfahu ime ojonuk vepkivsu. Hi fowkatit laik bitazuh owkav tidmozta peh zahiom kaf to jipelpev la. Alodo koh vedej zokhupkuz ho vu uvoekuwis zijmolmi vokezdom bebuobo opuke cugsuf wil gidazraf ifkocu bog fizefa."
  },
  "apiKey": "724173b2415d9e7497c52a6c3e97b2cb0bccc13c2900125932e405f4279ca188",
  "currency": {
    "code": "CLP",
    "name": "Chile Peso"
  }
}