{
  "name": "Rose Hale",
  "age": 31,
  "address": {
    "street": "Onpo Lane",
    "city": "Elulasub",
    "state": "CO",
    "zip": "09172"
  },
  "contact": {
    "phone": "(915) 928-5486",
    "servicePhone": "800716213"
  },
  "birthday": "2001-01-29T15:03:54.921Z",
  "ip": "147.178.91.29",
  "foo": "bar",
  "profile": {
    "about": "Ezo oheupe div avuab ete hag fe akuroh ev onkej nirvewu wibukga uruje ewehekig mige pomno ilu tu. Veb cusnub useuvu upeeszo pesejela ol dulwaf geom etegepa luratfa codaeh ehfu tehdaspu remwa haef. Doalmu ottoizi filioru je uliguze difakvur ateul kigsif gohuc to rute soij rolho asucu. Labpi rajaku cor zake ahoudlab zobefu toparilu hec ibi zonuzi ol juvwus od zesefe amo bip vigo. Ikfe uc anumis kakikev ad jotavim wi lultu mopavidi mekuv zi funcamgow divbo adli curdi togze idocen. Ni mabvok wukiw ki sirsu iro sovkiij madaah gini ba ga zikkujen makehep.",
    "bio": "Zev bud aribegej ivdufma cunahe wijberum nubelow afobu gom nukidu ufihehkif celufba moh daonuve de. Dirsu ottuji tivkawid jigi di usofomo tekepdus cec la ravlu awfe vu hupepel rukamzaz. Fode pewlawe adfagdow kegte ifaave mezekofeg gotcizo pami sas sowa waksinom mizuguor za pi heikanim puttaed. Noprilbap mico sojli lein le ewujagvi fe zubeca ri fadke kazomeran kav zuhugte top. Deij jo woslin tutjumko edujcu sottor cibin zefa kiwgoj umajuc ilukoto juzibiaj."
  },
  "apiKey": "ebeae2955f0f9800aa83d17e5c77f8a262939e5a9e3b05ddf453716f87612a7b",
  "currency": {
    "code": "MKD",
    "name": "Macedonia Denar"
  }
}