{
  "name": "Nannie Flores",
  "age": 40,
  "address": {
    "street": "Motac Street",
    "city": "Dohifo",
    "state": "NH",
    "zip": "89203"
  },
  "contact": {
    "phone": "(947) 696-7548",
    "servicePhone": "800755561"
  },
  "birthday": "1981-01-06T05:38:20.304Z",
  "ip": "39.169.238.231",
  "foo": "bar",
  "profile": {
    "about": "Meguuhe meen muabuoma dafi apriv perpuc zil roc cosudgag rubjino um hekzu usi bin. Tajisez kivuvef avagi tek meoriih tu pu ebhet aj rifag rucamlik gu nit rise. Nuhsefa ah wezunokiv nu ecbeju jud he gom bakdetaza riw ralhot kenti ecbev legidin zugoggu ro hiwet. Ujbeziz odacalol suvubmi caco cuw ponossa ot bipaz oro ger rocveew di dej. Gentav bowinnu tu ve pu vookifuc nos if kotnoh uchil kahen vasupcu. Desfodseh fi fucakov go panifbon wa feseh loshi mafpa ih atarez vejrete tebdagap dihnu jo sud.",
    "bio": "Li kenuti lumeid dur joulbuk juoleru muurupu ecici ubiet vin zu pefagpog fuj nit ogpesuk no fec. Wih rudcicog sacpev rep ohi muebko ol nofes befata pezi kimutu co ezod bo heoru dul sutog. Ruce ecle nuwavzek pezaset ovatujul lefegede lej nuf sodib tomfol wan bopej uvkipah fahsu wucpu. Cosoretu merwodlow fo pupgu vifawi wepum femuovu uj nog kiuku nideh cip tevuze guw picsej. Denow zopmo atazasas hi bumkuesa jikagku uz waoji vefa di gufefmum putcugza fes tuuvo mojipagi oze halilul."
  },
  "apiKey": "33dac394eab59aadcbfefef2edc772ee4dadd3ede93e37e743a8dadeade03323",
  "currency": {
    "code": "BZD",
    "name": "Belize Dollar"
  }
}